{
  "_fv": 34,
  "_type": "tool",
  "definition": {
    "renderType": 0,
    "texture": "knife",
    "customModelName": "Normal",
    "name": "Knife",
    "specialInfo": [],
    "creativeTab": {
      "value": "TOOLS"
    },
    "toolType": "Sword",
    "harvestLevel": 0,
    "efficiency": 4.0,
    "attackSpeed": 2.0,
    "enchantability": 2,
    "damageVsEntity": 3.0,
    "usageCount": 200,
    "blocksAffected": [],
    "hasGlow": false,
    "repairItems": [
      {
        "value": "Items.IRON_INGOT"
      }
    ],
    "immuneToFire": false,
    "stayInGridWhenCrafting": true,
    "damageOnCrafting": true
  }
}